bria_client/__init__.py
bria_client/py.typed
bria_client/clients/__init__.py
bria_client/clients/async_client.py
bria_client/clients/base.py
bria_client/clients/settings.py
bria_client/clients/sync_client.py
bria_client/engines/__init__.py
bria_client/engines/api_engine.py
bria_client/engines/bria_engine.py
bria_client/engines/base/__init__.py
bria_client/engines/base/async_http_request.py
bria_client/engines/base/base_http_request.py
bria_client/engines/base/sync_http_request.py
bria_client/toolkit/__init__.py
bria_client/toolkit/exception.py
bria_client/toolkit/image.py
bria_client/toolkit/models.py
bria_client/toolkit/response.py
bria_client-0.1.1.dist-info/METADATA
bria_client-0.1.1.dist-info/WHEEL
bria_client-0.1.1.dist-info/licenses/LICENSE
bria_client-0.1.1.dist-info/RECORD
