Metadata-Version: 2.4
Name: bria-client
Version: 0.1.1
Summary: Bria.ai Python SDK
Project-URL: Homepage, https://bria.ai
Project-URL: Documentation, https://docs.bria.ai
Project-URL: Repository, https://github.com/Bria-AI/bria-client
Project-URL: Issues, https://github.com/Bria-AI/bria-client/issues
Author: Bria.ai
Maintainer-email: omri <omriassa@bria.ai>, noam <noam@bria.ai>
License: MIT
License-File: LICENSE
Keywords: api-client,bria,image-generation,sdk
Classifier: Development Status :: 4 - Beta
Classifier: Intended Audience :: Developers
Classifier: License :: OSI Approved :: MIT License
Classifier: Programming Language :: Python :: 3
Classifier: Programming Language :: Python :: 3.10
Classifier: Programming Language :: Python :: 3.11
Classifier: Programming Language :: Python :: 3.12
Classifier: Programming Language :: Python :: 3.13
Classifier: Topic :: Multimedia :: Graphics
Classifier: Topic :: Software Development :: Libraries :: Python Modules
Requires-Python: >=3.10
Requires-Dist: httpx-retries<1.0,>=0.1
Requires-Dist: httpx<1.0,>=0.24
Requires-Dist: numpy<3.0,>=1.24
Requires-Dist: pillow<12.0,>=9.0
Requires-Dist: pydantic-settings<3.0,>=2.0
Requires-Dist: pydantic<3.0,>=2.0
Requires-Dist: requests
Requires-Dist: strenum; python_version < '3.11'
Requires-Dist: werkzeug<4.0,>=2.0
